seeker/__init__.py
seeker/highs.dll
seeker/libboost_filesystem-mt.dll
seeker/libstdc++-6.dll
seeker/libwinpthread-1.dll
seeker/seeker.2.1.0.cpython-310-darwin.so
seeker/seeker.2.1.0.cpython-310-linux.so
seeker/seeker.2.1.0.cpython-310-windows.pyd
seeker/seeker.2.1.0.cpython-311-darwin.so
seeker/seeker.2.1.0.cpython-311-linux.so
seeker/seeker.2.1.0.cpython-311-windows.pyd
seeker/seeker.2.1.0.cpython-312-darwin.so
seeker/seeker.2.1.0.cpython-312-linux.so
seeker/seeker.2.1.0.cpython-312-windows.pyd
seeker/seeker.2.1.0.cpython-313-darwin.so
seeker/seeker.2.1.0.cpython-313-linux.so
seeker/seeker.2.1.0.cpython-313-windows.pyd
seeker/seeker.2.1.0.cpython-38-darwin.so
seeker/seeker.2.1.0.cpython-38-linux.so
seeker/seeker.2.1.0.cpython-38-windows.pyd
seeker/seeker.2.1.0.cpython-39-darwin.so
seeker/seeker.2.1.0.cpython-39-linux.so
seeker/seeker.2.1.0.cpython-39-windows.pyd
seeker/seeker.dll
seeker/seeker.py
seeker/bin/coll
seeker/bin/coll-linux
seeker/bin/coll.exe
seeker/bin/hard
seeker/bin/hard.exe
seeker/scripts/collect.sh
seeker/scripts/darwin-collect.sh
seeker/scripts/darwin_seekeragg.sh
seeker/scripts/seekeragg.sh
ioseeker-0.2.5.dist-info/AUTHORS.rst
ioseeker-0.2.5.dist-info/LICENSE.rst
ioseeker-0.2.5.dist-info/METADATA
ioseeker-0.2.5.dist-info/WHEEL
ioseeker-0.2.5.dist-info/top_level.txt
ioseeker-0.2.5.dist-info/RECORD
