Metadata-Version: 2.1
Name: ioseeker
Version: 0.2.5
Summary: InsideOpt Seeker Distribution for Windows, Linux, and Mac
Author: Meinolf Sellmann
Author-email: info@insideopt.com
Keywords: insideopt,seeker,optimization
Classifier: Development Status :: 5 - Production/Stable
Classifier: Intended Audience :: Developers
Classifier: Natural Language :: English
Classifier: Programming Language :: Python :: 3.8
Classifier: Programming Language :: Python :: 3.9
Classifier: Programming Language :: Python :: 3.10
Classifier: Programming Language :: Python :: 3.11
Classifier: Programming Language :: Python :: 3.12
Classifier: Programming Language :: Python :: 3.13
Classifier: Operating System :: POSIX :: Linux
Classifier: Operating System :: MacOS :: MacOS X
Classifier: Operating System :: Microsoft :: Windows
Requires-Python: >=3.8.0
License-File: LICENSE.rst
License-File: AUTHORS.rst
